antelope_foreground/__init__.py
antelope_foreground/exceptions.py
antelope_foreground/foreground_catalog.py
antelope_foreground/foreground_query.py
antelope_foreground/frag_flow_lci.py
antelope_foreground/fragment_flows.py
antelope_foreground/lcia_dict.py
antelope_foreground/models.py
antelope_foreground/terminal_nodes.py
antelope_foreground/terminations.py
antelope_foreground/traversal_tests.py
antelope_foreground/data_sources/__init__.py
antelope_foreground/data_sources/calrecycle_lca.py
antelope_foreground/data_sources/tests/__init__.py
antelope_foreground/data_sources/tests/test_calrecycle.py
antelope_foreground/data_sources/tests/validate_calrecycle.py
antelope_foreground/entities/__init__.py
antelope_foreground/entities/fragment_editor.py
antelope_foreground/entities/fragments.py
antelope_foreground/entities/tree_isomorphism.py
antelope_foreground/entities/tests/__init__.py
antelope_foreground/entities/tests/test_fragments.py
antelope_foreground/implementations/__init__.py
antelope_foreground/implementations/foreground.py
antelope_foreground/interfaces/__init__.py
antelope_foreground/interfaces/iforeground.py
antelope_foreground/providers/__init__.py
antelope_foreground/providers/lc_foreground.py
antelope_foreground/providers/lcforeground.py
antelope_foreground/providers/oryx_client.py
antelope_foreground/providers/tests/__init__.py
antelope_foreground/providers/tests/test_foreground.py
antelope_foreground/providers/v1_client/__init__.py
antelope_foreground/providers/v1_client/antelope_lcia.py
antelope_foreground/providers/v1_client/antelope_v1.py
antelope_foreground/providers/v1_client/exceptions.py
antelope_foreground/providers/v1_client/foreground.py
antelope_foreground/providers/v1_client/index.py
antelope_foreground/providers/v1_client/quantity.py
antelope_foreground/providers/v1_client/tests/__init__.py
antelope_foreground/providers/v1_client/tests/test_antelope_v1_client.py
antelope_foreground/refs/__init__.py
antelope_foreground/refs/fragment_ref.py
antelope_foreground-0.3.7.dist-info/METADATA
antelope_foreground-0.3.7.dist-info/WHEEL
antelope_foreground-0.3.7.dist-info/top_level.txt
antelope_foreground-0.3.7.dist-info/RECORD
