Metadata-Version: 2.4
Name: antelope_foreground
Version: 0.3.7
Home-page: https://github.com/AntelopeLCA/foreground
Author: Brandon Kuczenski
Author-email: bkuczenski@ucsb.edu
Classifier: Development Status :: 4 - Beta
Classifier: Intended Audience :: Science/Research
Classifier: License :: OSI Approved :: BSD License
Classifier: Natural Language :: English
Classifier: Operating System :: OS Independent
Classifier: Programming Language :: Python :: 3
Classifier: Topic :: Scientific/Engineering
Requires-Python: >=3.6
Requires-Dist: antelope_interface>=0.3.3
Requires-Dist: antelope_core>=0.3.7
Dynamic: author
Dynamic: author-email
Dynamic: classifier
Dynamic: description
Dynamic: description-content-type
Dynamic: home-page
Dynamic: requires-dist
Dynamic: requires-python
